magpy/__init__.py
magpy/_virtual.py
magpy/magstim.py
magpy/rapid_config.yaml
magpy/rapid_system_info.yaml
MagPy_TMS-1.2.5.dist-info/LICENSE
MagPy_TMS-1.2.5.dist-info/METADATA
MagPy_TMS-1.2.5.dist-info/WHEEL
MagPy_TMS-1.2.5.dist-info/top_level.txt
MagPy_TMS-1.2.5.dist-info/RECORD
