Metadata-Version: 2.1
Name: MagPy-TMS
Version: 1.2.5
Summary: A Python toolbox for controlling Magstim TMS stimulators via serial communication
Home-page: http://github.com/nicolasmcnair/magpy
Author: Nicolas McNair
Author-email: nicolas.mcnair@sydney.edu.au
License: UNKNOWN
Keywords: TMS Magstim
Platform: UNKNOWN
Classifier: Development Status :: 5 - Production/Stable
Classifier: License :: OSI Approved :: GNU General Public License v3 (GPLv3)
Classifier: Programming Language :: Python :: 2.7
Classifier: Programming Language :: Python :: 3
Requires-Python: >=2.7, !=3.0.*, !=3.1.*, !=3.2.*
Requires-Dist: pyserial
